eres/__init__.py
eres-0.0.1.dist-info/METADATA
eres-0.0.1.dist-info/WHEEL
eres-0.0.1.dist-info/top_level.txt
eres-0.0.1.dist-info/RECORD
