Metadata-Version: 2.4
Name: eres
Version: 0.0.1
Summary: (e)ntity (res)olution with ibis
Author-email: ben <ben@politizen.org>
